<edmx:Edmx xmlns:edmx="http://docs.oasis-open.org/odata/ns/edmx" Version="4.0">
    <edmx:Reference Uri="https://sap.github.io/odata-vocabularies/vocabularies/Common.xml">
        <edmx:Include Namespace="com.sap.vocabularies.Common.v1" Alias="Common"/>
    </edmx:Reference>
    <edmx:Reference Uri="https://sap.github.io/odata-vocabularies/vocabularies/UI.xml">
        <edmx:Include Namespace="com.sap.vocabularies.UI.v1" Alias="UI"/>
    </edmx:Reference>
    <edmx:Reference Uri="/sap/opu/odata/sap/ZC_DM_MTR_PRESAMPLING_CON_CDS/$metadata">
        <edmx:Include Namespace="ZC_DM_MTR_PRESAMPLING_CON_CDS" Alias="SAP"/>
    </edmx:Reference>
    <edmx:DataServices>
        <Schema xmlns="http://docs.oasis-open.org/odata/ns/edm" Namespace="local">
            <Annotations Target="SAP.ZC_DM_MTR_PRESAMPLING_CONType">
                <Annotation Term="UI.LineItem">
                    <Collection>
                        <Record Type="UI.DataField">
                            <PropertyValue Property="Value" Path="matnr"/>
                            <Annotation Term="UI.Importance" EnumMember="UI.ImportanceType/High"/>
                        </Record>
                        <Record Type="UI.DataField">
                            <PropertyValue Property="Value" Path="equnr"/>
                        </Record>
                        <Record Type="UI.DataField">
                            <PropertyValue Property="Value" Path="serge"/>
                        </Record>
                        <Record Type="UI.DataField">
                            <PropertyValue Property="Value" Path="los"/>
                        </Record>
                        <Record Type="UI.DataField">
                            <PropertyValue Property="Value" Path="plombe"/>
                        </Record>
                        <Record Type="UI.DataField">
                            <PropertyValue Property="Value" Path="plombdat"/>
                        </Record>
                        <Record Type="UI.DataField">
                            <PropertyValue Property="Value" Path="bgljahr"/>
                        </Record>
                        <Record Type="UI.DataField">
                            <PropertyValue Property="Value" Path="vlzeit_dev"/>
                        </Record>
                        <Record Type="UI.DataField">
                            <PropertyValue Property="Value" Path="SealExpdat"/>
                        </Record>
                        <Record Type="UI.DataField">
                            <PropertyValue Property="Value" Path="bauform"/>
                        </Record>
                        <Record Type="UI.DataField">
                            <PropertyValue Property="Value" Path="vlzeitt"/>
                        </Record>
                        <Record Type="UI.DataField">
                            <PropertyValue Property="Value" Path="bauklas"/>
                        </Record>
                        <Record Type="UI.DataField">
                            <PropertyValue Property="Value" Path="b_lager"/>
                        </Record>
                        <Record Type="UI.DataField">
                            <PropertyValue Property="Value" Path="txt30"/>
                        </Record>
                        <Record Type="UI.DataField">
                            <PropertyValue Property="Value" Path="plodat"/>
                        </Record>
                        <Record Type="UI.DataField">
                            <PropertyValue Property="Value" Path="vlzeitti"/>
                        </Record>
                        <Record Type="UI.DataField">
                            <PropertyValue Property="Value" Path="SealExpdat"/>
                        </Record>
                        <Record Type="UI.DataField">
                            <PropertyValue Property="Value" Path="nxtSealExpdat"/>
                        </Record>
                        <Record Type="UI.DataField">
                            <PropertyValue Property="Value" Path="metfirm"/>
                        </Record>
                        <Record Type="UI.DataField">
                            <PropertyValue Property="Value" Path="Dev_Com"/>
                        </Record>
                    </Collection>
                </Annotation>
            </Annotations>
            <Annotations Target="SAP.ZC_DM_MTR_PRESAMPLING_CONType/matnr">
                <Annotation Term="Common.ValueList">
                    <Record Type="Common.ValueListType">
                        <PropertyValue Property="Parameters">
                            <Collection>
                                <Record Type="Common.ValueListParameterInOut">
                                    <PropertyValue Property="ValueListProperty" String="matnr"/>
                                    <PropertyValue Property="LocalDataProperty" PropertyPath="matnr"/>
                                </Record>
                            </Collection>
                        </PropertyValue>
                        <PropertyValue Property="CollectionPath" String="ZC_DM_MTR_PRESAMPLING_CON"/>
                        <PropertyValue Property="SearchSupported" Bool="true"/>
                    </Record>
                </Annotation>
            </Annotations>
        </Schema>
    </edmx:DataServices>
</edmx:Edmx>